aeronet_convert/__init__.py
aeronet_convert/__version__.py
aeronet_convert/rasterize.py
aeronet_convert/vectorize.py
aeronet_convert-0.2.5.dist-info/METADATA
aeronet_convert-0.2.5.dist-info/WHEEL
aeronet_convert-0.2.5.dist-info/top_level.txt
aeronet_convert-0.2.5.dist-info/RECORD
