Metadata-Version: 2.1
Name: aeronet-convert
Version: 0.2.5
Summary: Raster-vector conversion for deep learning with remote sensing data. Based on opencv, rasterio, shapely.
Home-page: 
Author: Geoalert
Author-email: hello@geoalert.io
License: MIT
Classifier: License :: OSI Approved :: MIT License
Classifier: Programming Language :: Python
Classifier: Programming Language :: Python :: 3
Classifier: Programming Language :: Python :: 3.6
Classifier: Programming Language :: Python :: Implementation :: CPython
Classifier: Programming Language :: Python :: Implementation :: PyPy
Requires-Python: >=3.6.0
Requires-Dist: opencv-python >=4.0.0
Requires-Dist: aeronet-raster ==0.2.5
Requires-Dist: aeronet-vector ==0.2.5
